sumbuddy/__about__.py
sumbuddy/__init__.py
sumbuddy/__main__.py
sumbuddy/exceptions.py
sumbuddy/filter.py
sumbuddy/hasher.py
sumbuddy/mapper.py
sum_buddy-1.0.0.dist-info/METADATA
sum_buddy-1.0.0.dist-info/WHEEL
sum_buddy-1.0.0.dist-info/entry_points.txt
sum_buddy-1.0.0.dist-info/licenses/LICENSE
sum_buddy-1.0.0.dist-info/RECORD
