Metadata-Version: 2.4
Name: sum-buddy
Version: 1.0.0
Summary: A command-line package to generate CSV with filepath, filename, checksum for all contents of given directory.
Project-URL: Homepage, https://github.com/Imageomics/sum-buddy
Project-URL: Repository, https://github.com/Imageomics/sum-buddy.git
Project-URL: Bug Tracker, https://github.com/Imageomics/sum-buddy/issues
Author-email: "Matthew J. Thompson" <thompson.m.j@outlook.com>, "Elizabeth G. Campolongo" <e.campolongo479@gmail.com>
License-File: LICENSE
Classifier: License :: OSI Approved :: MIT License
Classifier: Operating System :: OS Independent
Classifier: Programming Language :: Python :: 3
Requires-Python: >=3.10
Requires-Dist: pathspec
Requires-Dist: tqdm
Provides-Extra: dev
Requires-Dist: pre-commit; extra == 'dev'
Requires-Dist: pytest; extra == 'dev'
Requires-Dist: ruff; extra == 'dev'
Provides-Extra: keywords
Requires-Dist: checksum; extra == 'keywords'
Requires-Dist: csv; extra == 'keywords'
Requires-Dist: deduplication; extra == 'keywords'
Requires-Dist: file-verification; extra == 'keywords'
Requires-Dist: imageomics; extra == 'keywords'
Requires-Dist: images; extra == 'keywords'
Requires-Dist: md5; extra == 'keywords'
Requires-Dist: metadata; extra == 'keywords'
Requires-Dist: verifier; extra == 'keywords'
